concoction/__init__.py
concoction/core.py
concoction/values/__init__.py
concoction/values/dataclass.py
concoction/values/pydantic.py
concoction-0.1.4.dist-info/LICENSE
concoction-0.1.4.dist-info/METADATA
concoction-0.1.4.dist-info/WHEEL
concoction-0.1.4.dist-info/RECORD
