Metadata-Version: 2.3
Name: concoction
Version: 0.1.4
Summary: Library to inject configurations
License: MIT
Keywords: python,config,configuration,settings,injection,injector,configuration-management
Author: soapun
Requires-Python: >=3.8,<4
Classifier: Intended Audience :: Developers
Classifier: License :: OSI Approved :: MIT License
Classifier: Operating System :: OS Independent
Classifier: Programming Language :: Python
Classifier: Programming Language :: Python :: 3
Classifier: Programming Language :: Python :: 3.8
Classifier: Programming Language :: Python :: 3.9
Classifier: Programming Language :: Python :: 3.10
Classifier: Programming Language :: Python :: 3.11
Classifier: Programming Language :: Python :: 3.12
Classifier: Programming Language :: Python :: 3.13
Classifier: Topic :: Software Development :: Libraries :: Python Modules
Requires-Dist: bidict (>=0.23.1,<0.24.0)
Requires-Dist: pydantic (>2)
Requires-Dist: python-benedict (>=0.33.2,<0.34.0)
Project-URL: Homepage, https://github.com/soapun/concoction
Project-URL: Repository, https://github.com/soapun/concoction
